skeliner/__init__.py
skeliner/_core.py
skeliner/_state.py
skeliner/batch.py
skeliner/dataclass.py
skeliner/dx.py
skeliner/io.py
skeliner/pair.py
skeliner/post.py
skeliner/skeletonize.py
skeliner/plot/__init__.py
skeliner/plot/vis2d.py
skeliner/plot/vis3d.py
skeliner-0.2.3.dist-info/METADATA
skeliner-0.2.3.dist-info/WHEEL
skeliner-0.2.3.dist-info/licenses/LICENSE
skeliner-0.2.3.dist-info/RECORD
