Metadata-Version: 2.4
Name: skeliner
Version: 0.2.3
Summary: A lightweight neuromorphological mesh skeletonizer.
License-Expression: GPL-3.0-or-later
License-File: LICENSE
Requires-Python: >=3.10.0
Requires-Dist: igraph>=0.11.8
Requires-Dist: matplotlib>=3.10.3
Requires-Dist: numpy>=2.0.2
Requires-Dist: rtree>=1.4.1
Requires-Dist: scipy>=1.13.1
Requires-Dist: trimesh==4.7.4
Provides-Extra: 3d
Requires-Dist: vtk>=9.4.2; extra == '3d'
Provides-Extra: dev
Requires-Dist: ipykernel>=7.1.0; extra == 'dev'
Requires-Dist: maturin; extra == 'dev'
Requires-Dist: pytest; extra == 'dev'
Requires-Dist: ruff; extra == 'dev'
Requires-Dist: twine; extra == 'dev'
Requires-Dist: watermark>=2.5.0; extra == 'dev'
